misc_io_operations/__init__.py
misc_io_operations/misc_io_operations.py
misc_io_operations-1.3.3.dist-info/METADATA
misc_io_operations-1.3.3.dist-info/WHEEL
misc_io_operations-1.3.3.dist-info/top_level.txt
misc_io_operations-1.3.3.dist-info/RECORD
