Metadata-Version: 2.1
Name: misc-io-operations
Version: 1.3.3
Summary: Simplification of daily input/output operations
Home-page: https://github.com/GamerXZEN/misc_io_operations
Author: GamerXZEN
Author-email: codspecialops@gmail.com
License: MIT
Keywords: operations,input,output,input/output,miscellaneous,python
Platform: UNKNOWN
Classifier: Development Status :: 3 - Alpha
Classifier: Intended Audience :: Developers
Classifier: Topic :: Software Development :: Build Tools
Classifier: License :: OSI Approved :: MIT License
Classifier: Programming Language :: Python :: 3.7
Classifier: Programming Language :: Python :: 3.8
Classifier: Programming Language :: Python :: 3.9
Classifier: Programming Language :: Python :: 3.10
Classifier: Programming Language :: Python :: 3.11
Classifier: Programming Language :: Python :: 3.12
Requires-Dist: requests
